thpoker/__init__.py
thpoker/core.py
thpoker/exceptions.py
thpoker/game.py
thpoker/hardcore.py
thpoker/validators.py
THPoker-2.2.1.dist-info/LICENSE
THPoker-2.2.1.dist-info/METADATA
THPoker-2.2.1.dist-info/WHEEL
THPoker-2.2.1.dist-info/top_level.txt
THPoker-2.2.1.dist-info/RECORD
