Metadata-Version: 2.1
Name: THPoker
Version: 2.2.1
Summary: Texas Hold'em Poker tool
Home-page: https://github.com/YegorDB/THPoker
Author: Yegor Bitensky
License: UNKNOWN
Keywords: poker cards
Platform: UNKNOWN
Classifier: Development Status :: 5 - Production/Stable
Classifier: Intended Audience :: Developers
Classifier: Intended Audience :: Education
Classifier: Topic :: Games/Entertainment
Classifier: License :: OSI Approved :: Apache Software License
Classifier: Programming Language :: Python
Classifier: Programming Language :: Python :: 3
Classifier: Programming Language :: Python :: 3.8
Classifier: Programming Language :: Python :: 3.9
Classifier: Programming Language :: Python :: 3 :: Only
Requires-Python: >=3.8
Requires-Dist: CTHPoker
Requires-Dist: AGStuff
